com_digitalruiz_shopify_apis/__init__.py
com_digitalruiz_shopify_apis/shopify_apis.py
com_digitalruiz_shopify_apis-0.0.3.dist-info/LICENSE
com_digitalruiz_shopify_apis-0.0.3.dist-info/METADATA
com_digitalruiz_shopify_apis-0.0.3.dist-info/WHEEL
com_digitalruiz_shopify_apis-0.0.3.dist-info/top_level.txt
com_digitalruiz_shopify_apis-0.0.3.dist-info/RECORD
