Metadata-Version: 2.1
Name: com-digitalruiz-shopify-apis
Version: 0.0.3
Summary: A custom http client for shopify
Author-email: Reyes Ruiz <reyes@digitalruiz.com>
Project-URL: Homepage, https://github.com/reyesruiz/shopify_apis
Project-URL: Bug Tracker, https://github.com/reyesruiz/shopify_apis/issues
Classifier: Programming Language :: Python :: 3
Classifier: License :: OSI Approved :: MIT License
Classifier: Operating System :: OS Independent
Requires-Python: >=3.7
License-File: LICENSE
Requires-Dist: com-digitalruiz-my-logger
Requires-Dist: com-digitalruiz-shopify-http-client
